{"match_id":3791541293,"barracks_status_dire":63,"barracks_status_radiant":0,"chat":null,"cluster":201,"cosmetics":null,"dire_score":68,"dire_team_id":null,"draft_timings":null,"duration":2462,"engine":1,"first_blood_time":50,"game_mode":22,"human_players":10,"leagueid":0,"lobby_type":7,"match_seq_num":3293070713,"negative_votes":0,"objectives":null,"picks_bans":[{"is_pick":false,"hero_id":8,"team":0,"order":0}],"positive_votes":0,"radiant_gold_adv":null,"radiant_score":22,"radiant_team_id":null,"radiant_win":false,"radiant_xp_adv":null,"skill":1,"start_time":1521568738,"teamfights":null,"tower_status_dire":1844,"tower_status_radiant":0,"version":null,"players":[{"match_id":3791541293,"player_slot":0,"ability_targets":null,"ability_upgrades_arr":[5102,5104,5103,5104,5104,5105,5104,5102,5102,6141,5102,5105,5103,5103,6530,5103,5105,6207],"ability_uses":null,"account_id":null,"actions":null,"additional_units":null,"assists":9,"backpack_0":0,"backpack_1":0,"backpack_2":0,"buyback_log":null,"camps_stacked":null,"connection_log":null,"creeps_stacked":null,"damage":null,"damage_inflictor":null,"damage_inflictor_received":null,"damage_taken":null,"damage_targets":null,"deaths":16,"denies":4,"dn_t":null,"firstblood_claimed":null,"gold":1686,"gold_per_min":415,"gold_reasons":null,"gold_spent":11750,"gold_t":null,"hero_damage":18218,"hero_healing":0,"hero_hits":null,"hero_id":16,"item_0":1,"item_1":108,"item_2":190,"item_3":36,"item_4":46,"item_5":180,"item_uses":null,"kill_streaks":null,"killed":null,"killed_by":null,"kills":5,"kills_log":null,"lane_pos":null,"last_hits":205,"leaver_status":0,"level":22,"lh_t":null,"life_state":null,"max_hero_hit":null,"multi_kills":null,"obs":null,"obs_left_log":null,"obs_log":null,"obs_placed":null,"party_id":null,"party_size":null,"performance_others":null,"permanent_buffs":null,"pings":null,"pred_vict":null,"purchase":null,"purchase_log":null,"randomed":null,"repicked":null,"roshans_killed":null,"rune_pickups":null,"runes":null,"runes_log":null,"sen":null,"sen_left_log":null,"sen_log":null,"sen_placed":null,"stuns":null,"teamfight_participation":null,"times":null,"tower_damage":496,"towers_killed":null,"xp_per_min":525,"xp_reasons":null,"xp_t":null,"radiant_win":false,"start_time":1521568738,"duration":2462,"cluster":201,"lobby_type":7,"game_mode":22,"is_contributor":false,"patch":30,"region":10,"isRadiant":true,"win":0,"lose":1,"total_gold":17028,"total_xp":21542,"kills_per_min":0.12185215272136475,"kda":0,"abandons":0,"rank_tier":null,"cosmetics":[],"benchmarks":{"gold_per_min":{"raw":415,"pct":0.5899031811894883},"xp_per_min":{"raw":525,"pct":0.5491009681881052},"kills_per_min":{"raw":0.12185215272136474,"pct":0.5269709543568465},"last_hits_per_min":{"raw":4.995938261575954,"pct":0.8367911479944675},"hero_damage_per_min":{"raw":443.9805036555646,"pct":0.4094052558782849},"hero_healing_per_min":{"raw":0,"pct":0.8997233748271093},"tower_damage":{"raw":496,"pct":0.607192254495159},"stuns_per_min":{"raw":0,"pct":0},"lhten":{}}},{"match_id":3791541293,"player_slot":1,"ability_targets":null,"ability_upgrades_arr":[5372,5370,5372,5370,5372,5370,5372,5370,5372,5371,5372,5371,5372,5371,5371,5371,5371,5371],"ability_uses":null,"account_id":236095982,"actions":null,"additional_units":null,"assists":6,"backpack_0":0,"backpack_1":0,"backpack_2":0,"buyback_log":null,"camps_stacked":null,"connection_log":null,"creeps_stacked":null,"damage":null,"damage_inflictor":null,"damage_inflictor_received":null,"damage_taken":null,"damage_targets":null,"deaths":12,"denies":17,"dn_t":null,"firstblood_claimed":null,"gold":2350,"gold_per_min":372,"gold_reasons":null,"gold_spent":10405,"gold_t":null,"hero_damage":10829,"hero_healing":0,"hero_hits":null,"hero_id":74,"item_0":1,"item_1":77,"item_2":108,"item_3":36,"item_4":29,"item_5":65,"item_uses":null,"kill_streaks":null,"killed":null,"killed_by":null,"kills":4,"kills_log":null,"lane_pos":null,"last_hits":146,"leaver_status":0,"level":20,"lh_t":null,"life_state":null,"max_hero_hit":null,"multi_kills":null,"obs":null,"obs_left_log":null,"obs_log":null,"obs_placed":null,"party_id":null,"party_size":null,"performance_others":null,"permanent_buffs":null,"pings":null,"pred_vict":null,"purchase":null,"purchase_log":null,"randomed":null,"repicked":null,"roshans_killed":null,"rune_pickups":null,"runes":null,"runes_log":null,"sen":null,"sen_left_log":null,"sen_log":null,"sen_placed":null,"stuns":null,"teamfight_participation":null,"times":null,"tower_damage":0,"towers_killed":null,"xp_per_min":437,"xp_reasons":null,"xp_t":null,"personaname":"wos-","name":null,"last_login":null,"radiant_win":false,"start_time":1521568738,"duration":2462,"cluster":201,"lobby_type":7,"game_mode":22,"is_contributor":false,"patch":30,"region":10,"isRadiant":true,"win":0,"lose":1,"total_gold":15264,"total_xp":17931,"kills_per_min":0.0974817221770918,"kda":0,"abandons":0,"rank_tier":52,"cosmetics":[],"benchmarks":{"gold_per_min":{"raw":372,"pct":0.21082352941176472},"xp_per_min":{"raw":437,"pct":0.196},"kills_per_min":{"raw":0.09748172217709179,"pct":0.15011764705882352},"last_hits_per_min":{"raw":3.5580828594638505,"pct":0.2656470588235294},"hero_damage_per_min":{"raw":263.90739236393176,"pct":0.05835294117647059},"hero_healing_per_min":{"raw":0,"pct":0.9644705882352941},"tower_damage":{"raw":0,"pct":0.09929411764705882},"stuns_per_min":{"raw":0,"pct":0.001176470588235294},"lhten":{}}},{"match_id":3791541293,"player_slot":2,"ability_targets":null,"ability_upgrades_arr":[5458,5460,5459,5460,5458,5461,5459,5460,5458,6536,5460,5461,5458,5459,6056,5459,5461,6026],"ability_uses":null,"account_id":null,"actions":null,"additional_units":null,"assists":11,"backpack_0":0,"backpack_1":0,"backpack_2":0,"buyback_log":null,"camps_stacked":null,"connection_log":null,"creeps_stacked":null,"damage":null,"damage_inflictor":null,"damage_inflictor_received":null,"damage_taken":null,"damage_targets":null,"deaths":15,"denies":1,"dn_t":null,"firstblood_claimed":null,"gold":2264,"gold_per_min":327,"gold_reasons":null,"gold_spent":12310,"gold_t":null,"hero_damage":14702,"hero_healing":0,"hero_hits":null,"hero_id":87,"item_0":46,"item_1":100,"item_2":0,"item_3":108,"item_4":0,"item_5":40,"item_uses":null,"kill_streaks":null,"killed":null,"killed_by":null,"kills":6,"kills_log":null,"lane_pos":null,"last_hits":82,"leaver_status":0,"level":21,"lh_t":null,"life_state":null,"max_hero_hit":null,"multi_kills":null,"obs":null,"obs_left_log":null,"obs_log":null,"obs_placed":null,"party_id":null,"party_size":null,"performance_others":null,"permanent_buffs":null,"pings":null,"pred_vict":null,"purchase":null,"purchase_log":null,"randomed":null,"repicked":null,"roshans_killed":null,"rune_pickups":null,"runes":null,"runes_log":null,"sen":null,"sen_left_log":null,"sen_log":null,"sen_placed":null,"stuns":null,"teamfight_participation":null,"times":null,"tower_damage":622,"towers_killed":null,"xp_per_min":476,"xp_reasons":null,"xp_t":null,"radiant_win":false,"start_time":1521568738,"duration":2462,"cluster":201,"lobby_type":7,"game_mode":22,"is_contributor":false,"patch":30,"region":10,"isRadiant":true,"win":0,"lose":1,"total_gold":13417,"total_xp":19531,"kills_per_min":0.1462225832656377,"kda":1,"abandons":0,"rank_tier":null,"cosmetics":[],"benchmarks":{"gold_per_min":{"raw":327,"pct":0.6644736842105263},"xp_per_min":{"raw":476,"pct":0.7328947368421053},"kills_per_min":{"raw":0.1462225832656377,"pct":0.6855263157894737},"last_hits_per_min":{"raw":1.9983753046303818,"pct":0.8842105263157894},"hero_damage_per_min":{"raw":358.29406986190094,"pct":0.49078947368421055},"hero_healing_per_min":{"raw":0,"pct":0.7355263157894737},"tower_damage":{"raw":622,"pct":0.7526315789473684},"stuns_per_min":{"raw":0,"pct":0.8960526315789473},"lhten":{}}},{"match_id":3791541293,"player_slot":3,"ability_targets":null,"ability_upgrades_arr":[5003,5004,5003,5005,5004,5006,5004,5004,5005,5906,5003,5006,5005,5005,6606,5003,5006,6012,6607],"ability_uses":null,"account_id":null,"actions":null,"additional_units":null,"assists":7,"backpack_0":0,"backpack_1":0,"backpack_2":0,"buyback_log":null,"camps_stacked":null,"connection_log":null,"creeps_stacked":null,"damage":null,"damage_inflictor":null,"damage_inflictor_received":null,"damage_taken":null,"damage_targets":null,"deaths":7,"denies":42,"dn_t":null,"firstblood_claimed":null,"gold":1554,"gold_per_min":520,"gold_reasons":null,"gold_spent":20800,"gold_t":null,"hero_damage":12977,"hero_healing":0,"hero_hits":null,"hero_id":1,"item_0":208,"item_1":147,"item_2":46,"item_3":145,"item_4":32,"item_5":63,"item_uses":null,"kill_streaks":null,"killed":null,"killed_by":null,"kills":3,"kills_log":null,"lane_pos":null,"last_hits":318,"leaver_status":0,"level":25,"lh_t":null,"life_state":null,"max_hero_hit":null,"multi_kills":null,"obs":null,"obs_left_log":null,"obs_log":null,"obs_placed":null,"party_id":null,"party_size":null,"performance_others":null,"permanent_buffs":null,"pings":null,"pred_vict":null,"purchase":null,"purchase_log":null,"randomed":null,"repicked":null,"roshans_killed":null,"rune_pickups":null,"runes":null,"runes_log":null,"sen":null,"sen_left_log":null,"sen_log":null,"sen_placed":null,"stuns":null,"teamfight_participation":null,"times":null,"tower_damage":2620,"towers_killed":null,"xp_per_min":679,"xp_reasons":null,"xp_t":null,"radiant_win":false,"start_time":1521568738,"duration":2462,"cluster":201,"lobby_type":7,"game_mode":22,"is_contributor":false,"patch":30,"region":10,"isRadiant":true,"win":0,"lose":1,"total_gold":21337,"total_xp":27861,"kills_per_min":0.07311129163281885,"kda":1,"abandons":0,"rank_tier":null,"cosmetics":[],"benchmarks":{"gold_per_min":{"raw":520,"pct":0.26223337515683814},"xp_per_min":{"raw":679,"pct":0.4400878293601004},"kills_per_min":{"raw":0.07311129163281885,"pct":0.12421580928481807},"last_hits_per_min":{"raw":7.749796913078797,"pct":0.32434127979924715},"hero_damage_per_min":{"raw":316.25507717303003,"pct":0.26944792973651194},"hero_healing_per_min":{"raw":0,"pct":0.9159347553324969},"tower_damage":{"raw":2620,"pct":0.3450439146800502},"stuns_per_min":{"raw":0,"pct":0.01631116687578419},"lhten":{}}},{"match_id":3791541293,"player_slot":4,"ability_targets":null,"ability_upgrades_arr":[5357,5359,5357,5358,5357,5360,5357,5359,5359,5359,5982,5360,5358,5358,6973,5358],"ability_uses":null,"account_id":null,"actions":null,"additional_units":null,"assists":6,"backpack_0":46,"backpack_1":0,"backpack_2":0,"buyback_log":null,"camps_stacked":null,"connection_log":null,"creeps_stacked":null,"damage":null,"damage_inflictor":null,"damage_inflictor_received":null,"damage_taken":null,"damage_targets":null,"deaths":18,"denies":2,"dn_t":null,"firstblood_claimed":null,"gold":102,"gold_per_min":212,"gold_reasons":null,"gold_spent":7515,"gold_t":null,"hero_damage":10019,"hero_healing":0,"hero_hits":null,"hero_id":70,"item_0":11,"item_1":181,"item_2":50,"item_3":182,"item_4":36,"item_5":127,"item_uses":null,"kill_streaks":null,"killed":null,"killed_by":null,"kills":2,"kills_log":null,"lane_pos":null,"last_hits":47,"leaver_status":0,"level":17,"lh_t":null,"life_state":null,"max_hero_hit":null,"multi_kills":null,"obs":null,"obs_left_log":null,"obs_log":null,"obs_placed":null,"party_id":null,"party_size":null,"performance_others":null,"permanent_buffs":null,"pings":null,"pred_vict":null,"purchase":null,"purchase_log":null,"randomed":null,"repicked":null,"roshans_killed":null,"rune_pickups":null,"runes":null,"runes_log":null,"sen":null,"sen_left_log":null,"sen_log":null,"sen_placed":null,"stuns":null,"teamfight_participation":null,"times":null,"tower_damage":0,"towers_killed":null,"xp_per_min":338,"xp_reasons":null,"xp_t":null,"radiant_win":false,"start_time":1521568738,"duration":2462,"cluster":201,"lobby_type":7,"game_mode":22,"is_contributor":false,"patch":30,"region":10,"isRadiant":true,"win":0,"lose":1,"total_gold":8699,"total_xp":13869,"kills_per_min":0.0487408610885459,"kda":0,"abandons":0,"rank_tier":null,"cosmetics":[],"benchmarks":{"gold_per_min":{"raw":212,"pct":0.02063983488132095},"xp_per_min":{"raw":338,"pct":0.11558307533539731},"kills_per_min":{"raw":0.048740861088545896,"pct":0.05572755417956656},"last_hits_per_min":{"raw":1.1454102355808284,"pct":0.013415892672858616},"hero_damage_per_min":{"raw":244.16734362307068,"pct":0.10113519091847266},"hero_healing_per_min":{"raw":0,"pct":0.6800825593395253},"tower_damage":{"raw":0,"pct":0.1568627450980392},"stuns_per_min":{"raw":0,"pct":0.3333333333333333},"lhten":{}}},{"match_id":3791541293,"player_slot":128,"ability_targets":null,"ability_upgrades_arr":[5448,5450,5450,5451,5450,5452,5448,5450,5448,5451,5448,5452,5451,5451,5959,6003,5452,6041],"ability_uses":null,"account_id":null,"actions":null,"additional_units":null,"assists":30,"backpack_0":38,"backpack_1":0,"backpack_2":0,"buyback_log":null,"camps_stacked":null,"connection_log":null,"creeps_stacked":null,"damage":null,"damage_inflictor":null,"damage_inflictor_received":null,"damage_taken":null,"damage_targets":null,"deaths":8,"denies":0,"dn_t":null,"firstblood_claimed":null,"gold":2422,"gold_per_min":393,"gold_reasons":null,"gold_spent":13130,"gold_t":null,"hero_damage":13687,"hero_healing":0,"hero_hits":null,"hero_id":86,"item_0":1,"item_1":180,"item_2":36,"item_3":100,"item_4":46,"item_5":108,"item_uses":null,"kill_streaks":null,"killed":null,"killed_by":null,"kills":7,"kills_log":null,"lane_pos":null,"last_hits":88,"leaver_status":0,"level":22,"lh_t":null,"life_state":null,"max_hero_hit":null,"multi_kills":null,"obs":null,"obs_left_log":null,"obs_log":null,"obs_placed":null,"party_id":null,"party_size":null,"performance_others":null,"permanent_buffs":null,"pings":null,"pred_vict":null,"purchase":null,"purchase_log":null,"randomed":null,"repicked":null,"roshans_killed":null,"rune_pickups":null,"runes":null,"runes_log":null,"sen":null,"sen_left_log":null,"sen_log":null,"sen_placed":null,"stuns":null,"teamfight_participation":null,"times":null,"tower_damage":447,"towers_killed":null,"xp_per_min":521,"xp_reasons":null,"xp_t":null,"radiant_win":false,"start_time":1521568738,"duration":2462,"cluster":201,"lobby_type":7,"game_mode":22,"is_contributor":false,"patch":30,"region":10,"isRadiant":false,"win":1,"lose":0,"total_gold":16126,"total_xp":21378,"kills_per_min":0.17059301380991065,"kda":4,"abandons":0,"rank_tier":null,"cosmetics":[],"benchmarks":{"gold_per_min":{"raw":393,"pct":0.7739022111491747},"xp_per_min":{"raw":521,"pct":0.7240734973528495},"kills_per_min":{"raw":0.17059301380991065,"pct":0.7078791653690439},"last_hits_per_min":{"raw":2.1445978878960195,"pct":0.6163189037682965},"hero_damage_per_min":{"raw":333.55808285946387,"pct":0.34039240112114605},"hero_healing_per_min":{"raw":0,"pct":0.6060417315478044},"tower_damage":{"raw":447,"pct":0.572718779196512},"stuns_per_min":{"raw":0,"pct":0.0012457178449081284},"lhten":{}}},{"match_id":3791541293,"player_slot":129,"ability_targets":null,"ability_upgrades_arr":[5115,5114,5114,5115,5115,5117,5114,5114,5115,5910,5116,5117,5116,5116,6889,5116,5117,6020],"ability_uses":null,"account_id":375147419,"actions":null,"additional_units":null,"assists":28,"backpack_0":0,"backpack_1":0,"backpack_2":0,"buyback_log":null,"camps_stacked":null,"connection_log":null,"creeps_stacked":null,"damage":null,"damage_inflictor":null,"damage_inflictor_received":null,"damage_taken":null,"damage_targets":null,"deaths":7,"denies":2,"dn_t":null,"firstblood_claimed":null,"gold":1557,"gold_per_min":350,"gold_reasons":null,"gold_spent":12895,"gold_t":null,"hero_damage":16181,"hero_healing":0,"hero_hits":null,"hero_id":28,"item_0":102,"item_1":240,"item_2":63,"item_3":151,"item_4":36,"item_5":152,"item_uses":null,"kill_streaks":null,"killed":null,"killed_by":null,"kills":4,"kills_log":null,"lane_pos":null,"last_hits":70,"leaver_status":0,"level":20,"lh_t":null,"life_state":null,"max_hero_hit":null,"multi_kills":null,"obs":null,"obs_left_log":null,"obs_log":null,"obs_placed":null,"party_id":null,"party_size":null,"performance_others":null,"permanent_buffs":null,"pings":null,"pred_vict":null,"purchase":null,"purchase_log":null,"randomed":null,"repicked":null,"roshans_killed":null,"rune_pickups":null,"runes":null,"runes_log":null,"sen":null,"sen_left_log":null,"sen_log":null,"sen_placed":null,"stuns":null,"teamfight_participation":null,"times":null,"tower_damage":113,"towers_killed":null,"xp_per_min":440,"xp_reasons":null,"xp_t":null,"personaname":"Coraje >:v","name":null,"last_login":null,"radiant_win":false,"start_time":1521568738,"duration":2462,"cluster":201,"lobby_type":7,"game_mode":22,"is_contributor":false,"patch":30,"region":10,"isRadiant":false,"win":1,"lose":0,"total_gold":14361,"total_xp":18054,"kills_per_min":0.0974817221770918,"kda":4,"abandons":0,"rank_tier":63,"cosmetics":[],"benchmarks":{"gold_per_min":{"raw":350,"pct":0.42840095465393796},"xp_per_min":{"raw":440,"pct":0.39737470167064437},"kills_per_min":{"raw":0.09748172217709179,"pct":0.3204057279236277},"last_hits_per_min":{"raw":1.7059301380991063,"pct":0.18257756563245822},"hero_damage_per_min":{"raw":394.33793663688056,"pct":0.5912887828162291},"hero_healing_per_min":{"raw":0,"pct":0.8794749403341289},"tower_damage":{"raw":113,"pct":0.2535799522673031},"stuns_per_min":{"raw":0,"pct":0.0005966587112171838},"lhten":{}}},{"match_id":3791541293,"player_slot":130,"ability_targets":null,"ability_upgrades_arr":[5391,5393,5393,5391,5393,5394,5393,5391,5391,5906,5392,5394,5392,5392,6093,5392,5394,6712,6241],"ability_uses":null,"account_id":null,"actions":null,"additional_units":null,"assists":8,"backpack_0":241,"backpack_1":46,"backpack_2":0,"buyback_log":null,"camps_stacked":null,"connection_log":null,"creeps_stacked":null,"damage":null,"damage_inflictor":null,"damage_inflictor_received":null,"damage_taken":null,"damage_targets":null,"deaths":1,"denies":33,"dn_t":null,"firstblood_claimed":null,"gold":1242,"gold_per_min":743,"gold_reasons":null,"gold_spent":28025,"gold_t":null,"hero_damage":55546,"hero_healing":0,"hero_hits":null,"hero_id":76,"item_0":263,"item_1":96,"item_2":1,"item_3":123,"item_4":116,"item_5":247,"item_uses":null,"kill_streaks":null,"killed":null,"killed_by":null,"kills":36,"kills_log":null,"lane_pos":null,"last_hits":244,"leaver_status":0,"level":25,"lh_t":null,"life_state":null,"max_hero_hit":null,"multi_kills":null,"obs":null,"obs_left_log":null,"obs_log":null,"obs_placed":null,"party_id":null,"party_size":null,"performance_others":null,"permanent_buffs":null,"pings":null,"pred_vict":null,"purchase":null,"purchase_log":null,"randomed":null,"repicked":null,"roshans_killed":null,"rune_pickups":null,"runes":null,"runes_log":null,"sen":null,"sen_left_log":null,"sen_log":null,"sen_placed":null,"stuns":null,"teamfight_participation":null,"times":null,"tower_damage":7714,"towers_killed":null,"xp_per_min":808,"xp_reasons":null,"xp_t":null,"radiant_win":false,"start_time":1521568738,"duration":2462,"cluster":201,"lobby_type":7,"game_mode":22,"is_contributor":false,"patch":30,"region":10,"isRadiant":false,"win":1,"lose":0,"total_gold":30487,"total_xp":33154,"kills_per_min":0.8773354995938262,"kda":22,"abandons":0,"rank_tier":null,"cosmetics":[],"benchmarks":{"gold_per_min":{"raw":743,"pct":0.9612794612794613},"xp_per_min":{"raw":808,"pct":0.9183501683501684},"kills_per_min":{"raw":0.8773354995938262,"pct":0.9932659932659933},"last_hits_per_min":{"raw":5.946385052802599,"pct":0.6447811447811448},"hero_damage_per_min":{"raw":1353.6799350121853,"pct":0.9638047138047138},"hero_healing_per_min":{"raw":0,"pct":0.9629629629629629},"tower_damage":{"raw":7714,"pct":0.9814814814814815},"stuns_per_min":{"raw":0,"pct":0.0025252525252525255},"lhten":{}}},{"match_id":3791541293,"player_slot":131,"ability_targets":null,"ability_upgrades_arr":[6344,6461,6344,6346,6344,6343,6346,6344,6346,6461,6346,6343,6461,6461,5919,6463,6343,9060],"ability_uses":null,"account_id":42330286,"actions":null,"additional_units":null,"assists":18,"backpack_0":0,"backpack_1":0,"backpack_2":0,"buyback_log":null,"camps_stacked":null,"connection_log":null,"creeps_stacked":null,"damage":null,"damage_inflictor":null,"damage_inflictor_received":null,"damage_taken":null,"damage_targets":null,"deaths":3,"denies":2,"dn_t":null,"firstblood_claimed":null,"gold":4781,"gold_per_min":469,"gold_reasons":null,"gold_spent":14040,"gold_t":null,"hero_damage":17729,"hero_healing":0,"hero_hits":null,"hero_id":120,"item_0":1,"item_1":174,"item_2":208,"item_3":36,"item_4":180,"item_5":46,"item_uses":null,"kill_streaks":null,"killed":null,"killed_by":null,"kills":9,"kills_log":null,"lane_pos":null,"last_hits":127,"leaver_status":0,"level":24,"lh_t":null,"life_state":null,"max_hero_hit":null,"multi_kills":null,"obs":null,"obs_left_log":null,"obs_log":null,"obs_placed":null,"party_id":null,"party_size":null,"performance_others":null,"permanent_buffs":null,"pings":null,"pred_vict":null,"purchase":null,"purchase_log":null,"randomed":null,"repicked":null,"roshans_killed":null,"rune_pickups":null,"runes":null,"runes_log":null,"sen":null,"sen_left_log":null,"sen_log":null,"sen_placed":null,"stuns":null,"teamfight_participation":null,"times":null,"tower_damage":1941,"towers_killed":null,"xp_per_min":625,"xp_reasons":null,"xp_t":null,"personaname":"tiago,","name":null,"last_login":null,"radiant_win":false,"start_time":1521568738,"duration":2462,"cluster":201,"lobby_type":7,"game_mode":22,"is_contributor":false,"patch":30,"region":10,"isRadiant":false,"win":1,"lose":0,"total_gold":19244,"total_xp":25645,"kills_per_min":0.21933387489845654,"kda":6,"abandons":0,"rank_tier":53,"cosmetics":[],"benchmarks":{"gold_per_min":{"raw":469,"pct":0.5670212765957446},"xp_per_min":{"raw":625,"pct":0.6797872340425531},"kills_per_min":{"raw":0.21933387489845654,"pct":0.6808510638297872},"last_hits_per_min":{"raw":3.0950446791226645,"pct":0.2127659574468085},"hero_damage_per_min":{"raw":432.0633631194151,"pct":0.2925531914893617},"hero_healing_per_min":{"raw":0,"pct":0.8393617021276596},"tower_damage":{"raw":1941,"pct":0.8031914893617021},"stuns_per_min":{"raw":0,"pct":0.02127659574468085},"lhten":{}}},{"match_id":3791541293,"player_slot":132,"ability_targets":null,"ability_upgrades_arr":[5182,5184,5184,5182,5184,5185,5184,5182,5182,5960,5691,5185,5691,5691,6807,5691,5185,6128,6651],"ability_uses":null,"account_id":40466900,"actions":null,"additional_units":null,"assists":15,"backpack_0":0,"backpack_1":40,"backpack_2":0,"buyback_log":null,"camps_stacked":null,"connection_log":null,"creeps_stacked":null,"damage":null,"damage_inflictor":null,"damage_inflictor_received":null,"damage_taken":null,"damage_targets":null,"deaths":3,"denies":14,"dn_t":null,"firstblood_claimed":null,"gold":1792,"gold_per_min":590,"gold_reasons":null,"gold_spent":22315,"gold_t":null,"hero_damage":19279,"hero_healing":0,"hero_hits":null,"hero_id":41,"item_0":139,"item_1":147,"item_2":145,"item_3":63,"item_4":0,"item_5":123,"item_uses":null,"kill_streaks":null,"killed":null,"killed_by":null,"kills":11,"kills_log":null,"lane_pos":null,"last_hits":263,"leaver_status":0,"level":25,"lh_t":null,"life_state":null,"max_hero_hit":null,"multi_kills":null,"obs":null,"obs_left_log":null,"obs_log":null,"obs_placed":null,"party_id":null,"party_size":null,"performance_others":null,"permanent_buffs":null,"pings":null,"pred_vict":null,"purchase":null,"purchase_log":null,"randomed":null,"repicked":null,"roshans_killed":null,"rune_pickups":null,"runes":null,"runes_log":null,"sen":null,"sen_left_log":null,"sen_log":null,"sen_placed":null,"stuns":null,"teamfight_participation":null,"times":null,"tower_damage":7212,"towers_killed":null,"xp_per_min":735,"xp_reasons":null,"xp_t":null,"personaname":"V das Vadia","name":null,"last_login":"2017-05-22T04:07:57.253Z","radiant_win":false,"start_time":1521568738,"duration":2462,"cluster":201,"lobby_type":7,"game_mode":22,"is_contributor":false,"patch":30,"region":10,"isRadiant":false,"win":1,"lose":0,"total_gold":24209,"total_xp":30159,"kills_per_min":0.26807473598700243,"kda":6,"abandons":0,"rank_tier":43,"cosmetics":[],"benchmarks":{"gold_per_min":{"raw":590,"pct":0.7539654564681001},"xp_per_min":{"raw":735,"pct":0.8473739866055693},"kills_per_min":{"raw":0.26807473598700243,"pct":0.6531547409235108},"last_hits_per_min":{"raw":6.4094232331437855,"pct":0.697567853366232},"hero_damage_per_min":{"raw":469.8375304630382,"pct":0.5290800140994008},"hero_healing_per_min":{"raw":0,"pct":0.9643990130419458},"tower_damage":{"raw":7212,"pct":0.8198801550934085},"stuns_per_min":{"raw":0,"pct":0.0010574550581600281},"lhten":{}}}],"patch":30,"region":10}